django_celus_registry/__init__.py
django_celus_registry/admin.py
django_celus_registry/apps.py
django_celus_registry/migrations/0001_initial.py
django_celus_registry/migrations/0002_notification.py
django_celus_registry/migrations/0003_notification_reports.py
django_celus_registry/migrations/0004_alter_report_counter_release_and_more.py
django_celus_registry/migrations/__init__.py
django_celus_registry/models.py
django_celus_registry/serializers.py
django_celus_registry/tasks.py
django_celus_registry-0.4.0.dist-info/LICENSE
django_celus_registry-0.4.0.dist-info/METADATA
django_celus_registry-0.4.0.dist-info/WHEEL
django_celus_registry-0.4.0.dist-info/RECORD
