Metadata-Version: 2.1
Name: django-celus-registry
Version: 0.4.0
Summary: A simple scaper which download plublic data from the registry of COUNTER project
Home-page: https://github.com/Big-Dig-Data/django-celus-registry
License: MIT
Keywords: ntfy,email backend
Author: Stepan Henek
Author-email: stepan@bigdigdata.com
Requires-Python: >=3.8
Classifier: Framework :: Django
Classifier: License :: OSI Approved :: MIT License
Classifier: Programming Language :: Python :: 3
Classifier: Programming Language :: Python :: 3.8
Classifier: Programming Language :: Python :: 3.9
Classifier: Programming Language :: Python :: 3.10
Classifier: Programming Language :: Python :: 3.11
Classifier: Programming Language :: Python :: 3.12
Classifier: Programming Language :: Python :: 3.13
Classifier: Topic :: Software Development :: Libraries
Requires-Dist: celery (>=5.4.0)
Requires-Dist: django (>=4.2.6)
Requires-Dist: djangorestframework (>=3.14.0)
Requires-Dist: requests (>=2.31.0)
Project-URL: Repository, https://github.com/Big-Dig-Data/django-celus-registry
